{
    "latestEpisodePubDate": "2026-04-16T04:47:56.743Z",
    "pid": "65257ff6e8ce9deaf70a65e9",
    "title": "人民公园说AI",
    "brief": "如有干货，纯属巧合",
    "episodeCount": 125,
    "description": "这是由JustSayAI出品的陪伴型播客，三位合伙人跨越12小时时差，用老炮视角聊科技热点，只为做你的专属科技BGM！\n\n🔥 新朋友看这里 | 订阅「JustSayAI早晚报」\n每日两封，一键听报，碎片时间掌握行业动态：\n👉 https://m.justsayai.org/\n\n💎 老朋友进阶 | 加入 YouTube 专属会员\n解锁早晚报 + 深度研报 + 会员专属文字专栏：\n👉 https://www.youtube.com/@justsayaiorg/join\n\n👥 关于主播：\n小苏：前跨国新零售总经理 / 前SaaS营销总&500强市场 / 多家500强企业商业顾问\n老修：16年国际化产品老兵 / 前硅谷跨国公司产品技术负责人\n闲哥：中英加连续创业者 /先后融资3000万+美元/ 全球注册管理会计师\n\n🤝 商务合作：team@justsayai.org\n"
}